rust_enum.py
rust_enum-1.1.5.dist-info/METADATA
rust_enum-1.1.5.dist-info/WHEEL
rust_enum-1.1.5.dist-info/top_level.txt
rust_enum-1.1.5.dist-info/RECORD
