Metadata-Version: 2.1
Name: rust-enum
Version: 1.1.5
Summary: Rust-style enums
Home-page: https://github.com/girvel/rust_enum
Author: Nikita Girvel Dobrynin
Author-email: widauka@ya.ru
Classifier: Programming Language :: Python :: 3
Classifier: License :: OSI Approved :: MIT License
Classifier: Operating System :: OS Independent
Requires-Python: >=3.7
